dj_gpt/__init__.py
dj_gpt/base_chain.py
dj_gpt/song_finder.py
dj_gpt/summarizer.py
dj_gpt-0.1.0.dist-info/LICENSE
dj_gpt-0.1.0.dist-info/METADATA
dj_gpt-0.1.0.dist-info/WHEEL
dj_gpt-0.1.0.dist-info/RECORD
